LICENSE.txt
README.md
setup.cfg
setup.py
examples/__init__.py
examples/api1.py
examples/b1.py
examples/bwauth.py
examples/c1.py
examples/api/__init__.py
examples/basic/__init__.py
examples/watermark/__init__.py
examples/withauth/__init__.py
vicms/__init__.py
vicms/abst.py
vicms/database.py
vicms/filesyst.py
vicms.egg-info/PKG-INFO
vicms.egg-info/SOURCES.txt
vicms.egg-info/dependency_links.txt
vicms.egg-info/not-zip-safe
vicms.egg-info/requires.txt
vicms.egg-info/top_level.txt
vicms/api/__init__.py
vicms/api/withauth.py
vicms/basic/__init__.py
vicms/basic/withauth.py